{
  "sections": {
    "form": {
      "type": "contact-form",
      "settings": {
        "image_bg": "shopify:\/\/shop_images\/Capture_d_ecran_2023-10-10_a_12.23.20.png",
        "heading": "Votre prescripteur Cash-Back",
        "description": "Afin de vous envoyer le prescripteur, nous avons beosin de votre adresse postale. Nous l'enverrons seulement au professionnels de la santé concernés.",
        "liste": "Docteur\nKinésithérapeute\nAutre"
      }
    }
  },
  "order": [
    "form"
  ]
}
